[{"ID":1,"TITLE":"Семья шпиона"},{"ID":2,"TITLE":"Госпожа Кагуя: в любви как на войне"},{"ID":3,"TITLE":"Власть книжного червя 3"},{"ID":4,"TITLE":"Рандеву с жизнью 4"},{"ID":5,"TITLE":"У Коми проблемы с общением 2"},{"ID":6,"TITLE":"Летнее время"},{"ID":7,"TITLE":"Арифурэта: Сильнейший ремесленник в мире 2"},{"ID":8,"TITLE":"Реинкарнация безработного: История о приключениях в другом мире — Спецвыпуск"},{"ID":9,"TITLE":"Последний призыватель"},{"ID":10,"TITLE":"Живая любовь! Клуб идолов старшей школы Нидзигасаки 2"},{"ID":11,"TITLE":"Аоаси"},{"ID":12,"TITLE":"Любовь после порабощения мира"},{"ID":13,"TITLE":"Рыцарь-скелет в другом мире"},{"ID":14,"TITLE":"Величайший Повелитель Демонов перерождается как типичное ничтожество"},{"ID":15,"TITLE":"Деаймон"},{"ID":16,"TITLE":"Игра друзей"},{"ID":17,"TITLE":"Перестану быть героем"},{"ID":18,"TITLE":"Моя девушка не просто милашка"},{"ID":19,"TITLE":"Восхождение героя щита 2"},{"ID":20,"TITLE":"Непостижимая Ахарэн"},{"ID":21,"TITLE":"Влюблённые учёные и научное доказательство любви 2"},{"ID":22,"TITLE":"Городская дьяволица 2"},{"ID":23,"TITLE":"Сказание о демонах сакуры: Книга сказок"}]